machine_common_sense/__init__.py
machine_common_sense/_version.py
machine_common_sense/action.py
machine_common_sense/config_manager.py
machine_common_sense/controller.py
machine_common_sense/controller_events.py
machine_common_sense/controller_logger.py
machine_common_sense/controller_media.py
machine_common_sense/controller_output_handler.py
machine_common_sense/goal_metadata.py
machine_common_sense/history_writer.py
machine_common_sense/import_override.py
machine_common_sense/logging_config.py
machine_common_sense/material.py
machine_common_sense/object_metadata.py
machine_common_sense/parameter.py
machine_common_sense/plotter.py
machine_common_sense/recorder.py
machine_common_sense/return_status.py
machine_common_sense/reward.py
machine_common_sense/scene_history.py
machine_common_sense/serializer.py
machine_common_sense/step_metadata.py
machine_common_sense/stringifier.py
machine_common_sense/subscriber.py
machine_common_sense/unity_executable_provider.py
machine_common_sense/scripts/__init__.py
machine_common_sense/scripts/cache_addressables.py
machine_common_sense/scripts/change_file_names_to_cell_ids_make_videos.py
machine_common_sense/scripts/config_level1.ini
machine_common_sense/scripts/config_level1_debug.ini
machine_common_sense/scripts/config_level2.ini
machine_common_sense/scripts/config_level2_debug.ini
machine_common_sense/scripts/config_no_debug.ini
machine_common_sense/scripts/config_oracle.ini
machine_common_sense/scripts/config_oracle_debug.ini
machine_common_sense/scripts/config_with_debug.ini
machine_common_sense/scripts/extract_ground_truth_from_debug_files.py
machine_common_sense/scripts/getch_helper.py
machine_common_sense/scripts/run_action_file.py
machine_common_sense/scripts/run_follow_path.py
machine_common_sense/scripts/run_human_input.py
machine_common_sense/scripts/run_init_scenes.py
machine_common_sense/scripts/run_interactive_scenes_follow_path.py
machine_common_sense/scripts/run_interactive_scenes_last_action.py
machine_common_sense-0.7.4.dist-info/LICENSE
machine_common_sense-0.7.4.dist-info/METADATA
machine_common_sense-0.7.4.dist-info/WHEEL
machine_common_sense-0.7.4.dist-info/entry_points.txt
machine_common_sense-0.7.4.dist-info/top_level.txt
machine_common_sense-0.7.4.dist-info/RECORD
