Metadata-Version: 2.1
Name: machine-common-sense
Version: 0.7.4
Summary: Machine Common Sense Python API to Unity 3D Simulation Environment
Home-page: https://github.com/NextCenturyCorporation/MCS/
Maintainer: Next Century, a wholly owned subsidiary of CACI
Maintainer-email: mcs-ta2@machinecommonsense.com
License: Apache-2
Classifier: Development Status :: 5 - Production/Stable
Classifier: Programming Language :: Python
Classifier: Programming Language :: Python :: 3
Classifier: Programming Language :: Python :: 3.7
Classifier: Programming Language :: Python :: 3.8
Classifier: Programming Language :: Python :: 3.9
Classifier: Programming Language :: Python :: 3.10
Classifier: License :: OSI Approved :: Apache Software License
Classifier: Natural Language :: English
Classifier: Operating System :: OS Independent
Classifier: Intended Audience :: Science/Research
Classifier: Intended Audience :: Developers
Classifier: Topic :: Software Development
Classifier: Topic :: Scientific/Engineering
Classifier: Topic :: Scientific/Engineering :: Artificial Intelligence
Classifier: Topic :: Games/Entertainment :: Simulation
Classifier: Topic :: Multimedia :: Graphics
Classifier: Topic :: Multimedia :: Graphics :: 3D Rendering
Classifier: Typing :: Typed
Requires-Python: >=3.7,<3.11
License-File: LICENSE
Requires-Dist: ai2thor ==2.5.0
Requires-Dist: colour ==0.1.5
Requires-Dist: msgpack ==1.0.5
Requires-Dist: numpyencoder ==0.3.0
Requires-Dist: pydantic ==1.10.7
Requires-Dist: requests ==2.31.0
Requires-Dist: scikit-image ==0.19.3
Requires-Dist: typeguard ==3.0.2
Requires-Dist: Shapely ==1.7.1 ; python_version < "3.10"
Requires-Dist: importlib-metadata ==4.2.0 ; python_version < "3.8"
Requires-Dist: matplotlib ==3.5.3 ; python_version < "3.8"
Requires-Dist: opencv-python ==4.4.0.46 ; python_version <= "3.9"
Requires-Dist: opencv-python ==4.5.4.60 ; python_version >= "3.10"
Requires-Dist: Shapely ==1.8.5 ; python_version >= "3.10"
Requires-Dist: importlib-metadata ==6.3.0 ; python_version >= "3.8"
Requires-Dist: matplotlib ==3.7.1 ; python_version >= "3.8"
